{
"type": "FeatureCollection",
"name": "las_sendas",
"crs": { "type": "name", "properties": { "name": "urn:ogc:def:crs:OGC:1.3:CRS84" } },
"features": [
{ "type": "Feature", "properties": { "fid": 1 }, "geometry": { "type": "Point", "coordinates": [ -100.410162716130841, 25.657227663728868 ] } }
]
}
